setup.py
mobcrush/__init__.py
mobcrush/datatypes.py
mobcrush/main.py
mobcrush.egg-info/PKG-INFO
mobcrush.egg-info/SOURCES.txt
mobcrush.egg-info/dependency_links.txt
mobcrush.egg-info/requires.txt
mobcrush.egg-info/top_level.txt