Metadata-Version: 1.0
Name: mobcrush
Version: 0.1.0
Summary: Python Mobcrush API Wrapper
Home-page: https://github.com/jaynagpaul/mobcrush
Author: Jay Nagpaul
Author-email: spieswithin@gmail.com
License: MIT
Platform: UNKNOWN
